{
  "blog": {
    "blog_title": {
      "type": "input",
      "label": "Title",
      "required": true
    },
    "url": {
      "type": "input",
      "label": "Url",
      "required": true,
      "regex": "link"
    },
    "name": {
      "type": "input",
      "label": "Name",
      "required": true
    },
    "meta_data_title": {
      "type": "input",
      "label": "Meta Data Title",
      "required": true
    },
    "meta_data_description": {
      "type": "input",
      "label": "Meta Data Description",
      "required": true
    },
    "keywords": {
      "type": "input",
      "label": "Keywords",
      "required": true
    },
    "blog_key": {
      "type": "input",
      "label": "Blog Key",
      "required": true,
      "regex": "foregin_key"
    }
  },
  "article": {
    "article_title": {
      "type": "input",
      "label": "Title",
      "required": true
    },
    "date": {
      "type": "input-date",
      "label": "Date",
      "required": true
    },
    "lead": {
      "type": "input",
      "label": "Lead",
      "required": true
    },
    "url": {
      "type": "input",
      "label": "Url",
      "required": true,
      "regex": "link"
    },
    "meta_data_title": {
      "type": "input",
      "label": "Meta Data Title",
      "required": true
    },
    "meta_data_description": {
      "type": "input",
      "label": "Meta Data Description",
      "required": true
    },
    "keywords": {
      "type": "input",
      "label": "Keywords",
      "required": true
    },
    "author": {
      "type": "input",
      "label": "Author",
      "required": true
    },
    "photo_url": {
      "type": "input",
      "label": "Photo url",
      "required": true
    },
    "article_content": {
      "type": "input-html"
    },
    "post_tags": {
      "type": "input-array",
      "label": "Photo",
      "required": true
    },
    "blog_key": {
      "label": "Blog Key - automatic",
      "hidden": true,
      "key": true,
      "regex": "foregin_key"
    }
  },
  "podcast": {
    "podcast_title": {
      "type": "input",
      "label": "Title",
      "required": true
    },
    "url": {
      "type": "input",
      "label": "Url",
      "required": true,
      "regex": "link"
    },
    "name": {
      "type": "input",
      "label": "Name",
      "required": true
    },
    "meta_data_title": {
      "type": "input",
      "label": "Meta Data Title",
      "required": true
    },
    "meta_data_description": {
      "type": "input",
      "label": "Meta Data Description",
      "required": true
    },
    "keywords": {
      "type": "input",
      "label": "Keywords",
      "required": true
    },
    "podcast_key": {
      "type": "input",
      "label": "Podcast Key",
      "required": true,
      "regex": "foregin_key"
    }
  },
  "episode": {
    "episode_title": {
      "type": "input",
      "label": "Title",
      "required": true
    },
    "date": {
      "type": "input-date",
      "label": "Date",
      "required": true
    },
    "url": {
      "type": "input",
      "label": "Url",
      "required": true,
      "regex": "link"
    },
    "meta_data_title": {
      "type": "input",
      "label": "Meta Data Title",
      "required": true
    },
    "meta_data_description": {
      "type": "input",
      "label": "Meta Data Description",
      "required": true
    },
    "keywords": {
      "type": "input",
      "label": "Keywords",
      "required": true
    },
    "author": {
      "type": "input",
      "label": "Author",
      "required": true
    },
    "photo_url": {
      "type": "input",
      "label": "Photo url",
      "required": true
    },
    "announcement_url": {
      "type": "input",
      "label": "Announcement url",
      "required": true
    },
    "episode_content": {
      "type": "input-html"
    },
    "episode_tags": {
      "type": "input-array",
      "label": "Photo",
      "required": true
    },
    "podcast_key": {
      "label": "Podcast Key - automatic",
      "hidden": true,
      "key": true,
      "regex": "foregin_key"
    }
  },
  "users": {
    "nick_name": {
      "type": "input",
      "label": "Nick Name"
    },
    "email": {
      "type": "input",
      "label": "Email",
      "dataType": "email",
      "regex": "email"
    },
    "user_password": {
      "type": "input",
      "label": "User Password",
      "dataType": "password"
    },
    "access_lvl": {
      "type": "input",
      "label": "Access Lvl"
    }
  },
  "pages": {
    "name": {
      "type": "input",
      "label": "Page Name",
      "required": true
    },
    "page_content": {
      "type": "input-html"
    },
    "meta_data_title": {
      "type": "input",
      "label": "Meta Data Title",
      "required": true
    },
    "meta_data_description": {
      "type": "input",
      "label": "Meta Data Description",
      "required": true
    },
    "url": {
      "type": "input",
      "label": "Url",
      "required": true,
      "regex": "link"
    },
    "page_category": {
      "type": "input",
      "label": "Page Key",
      "required": true,
      "regex": "foregin_key"
    },
    "keywords": {
      "type": "input",
      "label": "Keywords",
      "required": true
    }
  },
  "menu": {
    "label": {
      "type": "input",
      "label": "Name",
      "required": true
    },
    "url_id": {
      "type": "dropdown",
      "label": "Choose URL",
      "required": true,
      "dropdown_link": "url"
    },
    "menu_order": {
      "label": "Menu Number - automatic",
      "hidden": true,
      "value_type": "number"
    },
    "parent_id": {
      "label": "Parent ID - automatic",
      "hidden": true,
      "value_type": "null"
    }
  }
}
